{
    "comments": [
        {
            "id": "68835ee56a4db1.35087207",
            "board_id": "15",
            "member_id": "mvc",
            "comment": "asd"
        },
        {
            "id": "68835efa4e3297.87618761",
            "board_id": "15",
            "member_id": "mvc",
            "comment": "asd"
        },
        {
            "id": "68835f28266c15.10671661",
            "board_id": "68833bfebd48a1.77181948",
            "member_id": "mvc",
            "comment": "asd"
        },
        {
            "id": "68835f342ecfd0.10231842",
            "board_id": "68833bfebd48a1.77181948",
            "member_id": "mvc",
            "comment": "asd"
        },
        {
            "id": "68835f74bc7fa9.37216557",
            "board_id": "68833260dca544.07939699",
            "member_id": "mvc",
            "comment": "asd"
        },
        {
            "id": "68835f7e164857.52130481",
            "board_id": "68833bf7138124.85808726",
            "member_id": "mvc",
            "comment": "asdasd"
        },
        {
            "id": "6883b65c6ffba1.85420800",
            "board_id": "68833bf7138124.85808726",
            "member_id": "mvc",
            "comment": "asd"
        },
        {
            "id": "68846dc7dd50d2.65590116",
            "board_id": "68833260dca544.07939699",
            "member_id": "mvc",
            "comment": "asd"
        }
    ]
}